datappkit/__init__.py
datappkit/datapp.py
datappkit/common/__init__.py
datappkit/common/config.py
datappkit/common/datapp_response.py
datappkit/common/quota_manager.py
datappkit/common/user_manager.py
datappkit/controller/__init__.py
datappkit/controller/batches_controller.py
datappkit/controller/file_controller.py
datappkit/controller/label_controller.py
datappkit/controller/requirement_controller.py
datappkit/controller/user_controller.py
datappkit/services/__init__.py
datappkit/services/base_request.py
datappkit/services/batches_service.py
datappkit/services/file_service.py
datappkit/services/label_service.py
datappkit/services/requirement_service.py
datappkit/services/user_service.py
datappkit/utils/__init__.py
datappkit/utils/file_utils.py
tests/__init__.py
tests/test_basic.py
tests/test_batch.py
tests/test_file.py
tests/test_label.py
tests/test_login.py
tests/test_otp.py
tests/test_requirement.py
tests/test_token.py
tests/test_user.py
datappkit-0.0.9.dist-info/METADATA
datappkit-0.0.9.dist-info/WHEEL
datappkit-0.0.9.dist-info/top_level.txt
datappkit-0.0.9.dist-info/RECORD
