Metadata-Version: 2.1
Name: datappkit
Version: 0.0.9
Summary: datapp team kit wrapper library
Home-page: https://git-core.megvii-inc.com/brain/label/infrastructure/data-service-sdk
Author: datapp
Author-email: baojiarui@megvii.com
License: UNKNOWN
Platform: UNKNOWN
Classifier: License :: Other/Proprietary License
Requires-Python: >=3.5
Requires-Dist: requests (~=2.27.1)
